{
    "data": [
        {
            "accountType": 1,
            "amount": 2921262,
            "assetMode": 0,
            "canBidAmount": 2921262,
            "detailTitle": "个人借款 WZUQGQZ9JYR",
            "detailUrl": "https://m.huli.com/1.1/bid/detail/706362032779003993/zrb",
            "fedPrdType": 0,
            "id": 706471122779005125,
            "idStr": "817507583880113093",
            "interestRate": 850,
            "interestType": "协议约定年化利率",
            "isFixedRepay": 0,
            "isSeckill": 0,
            "isSelfTransfer": 0,
            "isTransfer": 1,
            "isapp": 0,
            "isfresh": 0,
            "loanType": 0,
            "percent": 0,
            "periods": "9个月26天",
            "principalDiscountRate": 10000,
            "productType": "zrb",
            "raiseInterestRate": 0,
            "realStatus": 1,
            "remainingAmounts": 0,
            "repayMode": "先息后本",
            "repayModeInt": 0,
            "status": 1,
            "statusText": "抢",
            "subType": 0,
            "title": "个人借款 WZUQGQZ9JYR",
            "transRule": 0,
            "ztbPayAnyTime": 0
        },
        {
            "accountType": 1,
            "amount": 4029813,
            "assetMode": 0,
            "canBidAmount": 4029813,
            "detailTitle": "个人借款 QZDG4GNG20S",
            "detailUrl": "https://m.huli.com/1.1/bid/detail/695369091668994333/zrb",
            "fedPrdType": 0,
            "id": 473180209446773093,
            "idStr": "473032729446775245",
            "interestRate": 850,
            "interestType": "协议约定年化利率",
            "isFixedRepay": 0,
            "isSeckill": 0,
            "isSelfTransfer": 0,
            "isTransfer": 1,
            "isapp": 0,
            "isfresh": 0,
            "loanType": 0,
            "percent": 0,
            "periods": "9个月26天",
            "principalDiscountRate": 10000,
            "productType": "zrb",
            "raiseInterestRate": 0,
            "realStatus": 1,
            "remainingAmounts": 0,
            "repayMode": "先息后本",
            "repayModeInt": 0,
            "status": 1,
            "statusText": "抢",
            "subType": 0,
            "title": "个人借款 QZDG4GNG20S",
            "transRule": 0,
            "ztbPayAnyTime": 0
        },
        {
            "accountType": 1,
            "amount": 777796,
            "assetMode": 0,
            "canBidAmount": 777796,
            "detailTitle": "企业借款 YZQDULMXDVX",
            "detailUrl": "https://m.huli.com/1.1/bid/detail/817479183880113133/zrb",
            "fedPrdType": 0,
            "id": 362037768335665245,
            "idStr": "706367962779005385",
            "interestRate": 850,
            "interestType": "协议约定年化利率",
            "isFixedRepay": 0,
            "isSeckill": 0,
            "isSelfTransfer": 0,
            "isTransfer": 1,
            "isapp": 0,
            "isfresh": 0,
            "loanType": 0,
            "percent": 0,
            "periods": "9个月26天",
            "principalDiscountRate": 10000,
            "productType": "zrb",
            "raiseInterestRate": 0,
            "realStatus": 1,
            "remainingAmounts": 0,
            "repayMode": "先息后本",
            "repayModeInt": 0,
            "status": 1,
            "statusText": "抢",
            "subType": 0,
            "title": "企业借款 YZQDULMXDVX",
            "transRule": 0,
            "ztbPayAnyTime": 0
        },
        {
            "accountType": 1,
            "amount": 503,
            "assetMode": 0,
            "canBidAmount": 503,
            "detailTitle": "企业借款 HZX7TAUWCLO",
            "detailUrl": "https://m.huli.com/1.1/bid/detail/362908448335665365/zrb",
            "fedPrdType": 0,
            "id": 584263090557883173,
            "idStr": "706409352779005285",
            "interestRate": 750,
            "interestType": "协议约定年化利率",
            "isFixedRepay": 0,
            "isSeckill": 0,
            "isSelfTransfer": 0,
            "isTransfer": 1,
            "isapp": 0,
            "isfresh": 0,
            "loanType": 0,
            "percent": 0,
            "periods": "4个月25天",
            "principalDiscountRate": 10000,
            "productType": "zrb",
            "raiseInterestRate": 0,
            "realStatus": 1,
            "remainingAmounts": 0,
            "repayMode": "先息后本",
            "repayModeInt": 0,
            "status": 1,
            "statusText": "抢",
            "subType": 0,
            "title": "企业借款 HZX7TAUWCLO",
            "transRule": 0,
            "ztbPayAnyTime": 0
        },
        {
            "accountType": 1,
            "amount": 602490,
            "assetMode": 0,
            "canBidAmount": 351487,
            "detailTitle": "个人借款 ZZD7KOEHXKX",
            "detailUrl": "https://m.huli.com/1.1/bid/detail/584268750557883253/zrb",
            "fedPrdType": 0,
            "id": 695393001668993113,
            "idStr": "362037448335663073",
            "interestRate": 850,
            "interestType": "协议约定年化利率",
            "isFixedRepay": 0,
            "isSeckill": 0,
            "isSelfTransfer": 0,
            "isTransfer": 1,
            "isapp": 0,
            "isfresh": 0,
            "loanType": 0,
            "percent": 4167,
            "periods": "7个月12天",
            "principalDiscountRate": 10000,
            "productType": "zrb",
            "raiseInterestRate": 0,
            "realStatus": 1,
            "remainingAmounts": 0,
            "repayMode": "先息后本",
            "repayModeInt": 0,
            "status": 1,
            "statusText": "抢",
            "subType": 0,
            "title": "个人借款 ZZD7KOEHXKX",
            "transRule": 0,
            "ztbPayAnyTime": 0
        },
        {
            "accountType": 1,
            "amount": 303129,
            "assetMode": 0,
            "canBidAmount": 303129,
            "detailTitle": "个人借款 DZYYSBWRML2",
            "detailUrl": "https://m.huli.com/1.1/bid/detail/695379791668994313/zrb",
            "fedPrdType": 0,
            "id": 706497972779003113,
            "idStr": "584204040557883073",
            "interestRate": 850,
            "interestType": "协议约定年化利率",
            "isFixedRepay": 0,
            "isSeckill": 0,
            "isSelfTransfer": 0,
            "isTransfer": 1,
            "isapp": 0,
            "isfresh": 0,
            "loanType": 0,
            "percent": 0,
            "periods": "6个月7天",
            "principalDiscountRate": 10000,
            "productType": "zrb",
            "raiseInterestRate": 0,
            "realStatus": 1,
            "remainingAmounts": 0,
            "repayMode": "先息后本",
            "repayModeInt": 0,
            "status": 1,
            "statusText": "抢",
            "subType": 0,
            "title": "个人借款 DZYYSBWRML2",
            "transRule": 0,
            "ztbPayAnyTime": 0
        },
        {
            "accountType": 1,
            "amount": 303342,
            "assetMode": 0,
            "canBidAmount": 303342,
            "detailTitle": "房易贷 QZHZLZWJZDA",
            "detailUrl": "https://m.huli.com/1.1/bid/detail/584231300557885285/zrb",
            "fedPrdType": 0,
            "id": 473130399446775365,
            "idStr": "584227260557885385",
            "interestRate": 850,
            "interestType": "协议约定年化利率",
            "isFixedRepay": 0,
            "isSeckill": 0,
            "isSelfTransfer": 0,
            "isTransfer": 1,
            "isapp": 0,
            "isfresh": 0,
            "loanType": 0,
            "percent": 0,
            "periods": "5个月4天",
            "principalDiscountRate": 10000,
            "productType": "zrb",
            "raiseInterestRate": 0,
            "realStatus": 1,
            "remainingAmounts": 0,
            "repayMode": "先息后本",
            "repayModeInt": 0,
            "status": 1,
            "statusText": "抢",
            "subType": 0,
            "title": "房易贷 QZHZLZWJZDA",
            "transRule": 0,
            "ztbPayAnyTime": 0
        },
        {
            "accountType": 1,
            "amount": 1006653,
            "assetMode": 0,
            "canBidAmount": 1006653,
            "detailTitle": "个人借款 RZABZYZDFQI",
            "detailUrl": "https://m.huli.com/1.1/bid/detail/362096698335663193/zrb",
            "fedPrdType": 0,
            "id": 473106799446773113,
            "idStr": "584243260557885365",
            "interestRate": 850,
            "interestType": "协议约定年化利率",
            "isFixedRepay": 0,
            "isSeckill": 0,
            "isSelfTransfer": 0,
            "isTransfer": 1,
            "isapp": 0,
            "isfresh": 0,
            "loanType": 0,
            "percent": 0,
            "periods": "7个月23天",
            "principalDiscountRate": 10000,
            "productType": "zrb",
            "raiseInterestRate": 0,
            "realStatus": 1,
            "remainingAmounts": 0,
            "repayMode": "先息后本",
            "repayModeInt": 0,
            "status": 1,
            "statusText": "抢",
            "subType": 0,
            "title": "个人借款 RZABZYZDFQI",
            "transRule": 0,
            "ztbPayAnyTime": 0
        },
        {
            "accountType": 1,
            "amount": 945260,
            "assetMode": 0,
            "canBidAmount": 945260,
            "detailTitle": "企业借款 MZ1DZMKADOY",
            "detailUrl": "https://m.huli.com/1.1/bid/detail/362138958335663153/zrb",
            "fedPrdType": 0,
            "id": 584360270557883153,
            "idStr": "362140078335663913",
            "interestRate": 750,
            "interestType": "协议约定年化利率",
            "isFixedRepay": 0,
            "isSeckill": 0,
            "isSelfTransfer": 0,
            "isTransfer": 1,
            "isapp": 0,
            "isfresh": 0,
            "loanType": 0,
            "percent": 0,
            "periods": "4个月22天",
            "principalDiscountRate": 10000,
            "productType": "zrb",
            "raiseInterestRate": 0,
            "realStatus": 1,
            "remainingAmounts": 0,
            "repayMode": "先息后本",
            "repayModeInt": 0,
            "status": 1,
            "statusText": "抢",
            "subType": 0,
            "title": "企业借款 MZ1DZMKADOY",
            "transRule": 0,
            "ztbPayAnyTime": 0
        },
        {
            "accountType": 1,
            "amount": 559448,
            "assetMode": 0,
            "canBidAmount": 559448,
            "detailTitle": "个人借款 ZZH4CKCXKUG",
            "detailUrl": "https://m.huli.com/1.1/bid/detail/695468141668993293/zrb",
            "fedPrdType": 0,
            "id": 817537933880113013,
            "idStr": "362004508335665105",
            "interestRate": 850,
            "interestType": "协议约定年化利率",
            "isFixedRepay": 0,
            "isSeckill": 0,
            "isSelfTransfer": 0,
            "isTransfer": 1,
            "isapp": 0,
            "isfresh": 0,
            "loanType": 0,
            "percent": 0,
            "periods": "10个月18天",
            "principalDiscountRate": 10000,
            "productType": "zrb",
            "raiseInterestRate": 0,
            "realStatus": 1,
            "remainingAmounts": 0,
            "repayMode": "先息后本",
            "repayModeInt": 0,
            "status": 1,
            "statusText": "抢",
            "subType": 0,
            "title": "个人借款 ZZH4CKCXKUG",
            "transRule": 0,
            "ztbPayAnyTime": 0
        },
        {
            "accountType": 1,
            "amount": 432562,
            "assetMode": 0,
            "canBidAmount": 432562,
            "detailTitle": "房易贷 CZH5IVEA5X4",
            "detailUrl": "https://m.huli.com/1.1/bid/detail/695470271668995485/zrb",
            "fedPrdType": 0,
            "id": 362165028335663033,
            "idStr": "695417541668993273",
            "interestRate": 850,
            "interestType": "协议约定年化利率",
            "isFixedRepay": 0,
            "isSeckill": 0,
            "isSelfTransfer": 0,
            "isTransfer": 1,
            "isapp": 0,
            "isfresh": 0,
            "loanType": 0,
            "percent": 0,
            "periods": "5个月18天",
            "principalDiscountRate": 10000,
            "productType": "zrb",
            "raiseInterestRate": 0,
            "realStatus": 1,
            "remainingAmounts": 0,
            "repayMode": "先息后本",
            "repayModeInt": 0,
            "status": 1,
            "statusText": "抢",
            "subType": 0,
            "title": "房易贷 CZH5IVEA5X4",
            "transRule": 0,
            "ztbPayAnyTime": 0
        },
        {
            "accountType": 1,
            "amount": 177688,
            "assetMode": 0,
            "canBidAmount": 177688,
            "detailTitle": "企业借款 TZF09EJS50L",
            "detailUrl": "https://m.huli.com/1.1/bid/detail/695341721668993233/zrb",
            "fedPrdType": 0,
            "id": 584373040557885365,
            "idStr": "473270019446775205",
            "interestRate": 850,
            "interestType": "协议约定年化利率",
            "isFixedRepay": 0,
            "isSeckill": 0,
            "isSelfTransfer": 0,
            "isTransfer": 1,
            "isapp": 0,
            "isfresh": 0,
            "loanType": 0,
            "percent": 0,
            "periods": "9个月13天",
            "principalDiscountRate": 10000,
            "productType": "zrb",
            "raiseInterestRate": 0,
            "realStatus": 1,
            "remainingAmounts": 0,
            "repayMode": "先息后本",
            "repayModeInt": 0,
            "status": 1,
            "statusText": "抢",
            "subType": 0,
            "title": "企业借款 TZF09EJS50L",
            "transRule": 0,
            "ztbPayAnyTime": 0
        },
        {
            "accountType": 1,
            "amount": 2762866,
            "assetMode": 0,
            "canBidAmount": 2611010,
            "detailTitle": "个人借款 RZTKO9PUGYW",
            "detailUrl": "https://m.huli.com/1.1/bid/detail/706461912779005285/zrb",
            "fedPrdType": 0,
            "id": 473299299446773293,
            "idStr": "362132628335663033",
            "interestRate": 950,
            "interestType": "协议约定年化利率",
            "isFixedRepay": 0,
            "isSeckill": 0,
            "isSelfTransfer": 0,
            "isTransfer": 1,
            "isapp": 0,
            "isfresh": 0,
            "loanType": 0,
            "percent": 550,
            "periods": "33个月17天",
            "principalDiscountRate": 10000,
            "productType": "zrb",
            "raiseInterestRate": 0,
            "realStatus": 1,
            "remainingAmounts": 0,
            "repayMode": "等额本息",
            "repayModeInt": 0,
            "status": 1,
            "statusText": "抢",
            "subType": 0,
            "title": "个人借款 RZTKO9PUGYW",
            "transRule": 0,
            "ztbPayAnyTime": 0
        },
        {
            "accountType": 1,
            "amount": 1816224,
            "assetMode": 0,
            "canBidAmount": 1816224,
            "detailTitle": "企业借款 WZB9TOEJ1IA",
            "detailUrl": "https://m.huli.com/1.1/bid/detail/584367960557885405/zrb",
            "fedPrdType": 0,
            "id": 473241709446775245,
            "idStr": "695475041668995485",
            "interestRate": 850,
            "interestType": "协议约定年化利率",
            "isFixedRepay": 0,
            "isSeckill": 0,
            "isSelfTransfer": 0,
            "isTransfer": 1,
            "isapp": 0,
            "isfresh": 0,
            "loanType": 0,
            "percent": 0,
            "periods": "9个月13天",
            "principalDiscountRate": 10000,
            "productType": "zrb",
            "raiseInterestRate": 0,
            "realStatus": 1,
            "remainingAmounts": 0,
            "repayMode": "先息后本",
            "repayModeInt": 0,
            "status": 1,
            "statusText": "抢",
            "subType": 0,
            "title": "企业借款 WZB9TOEJ1IA",
            "transRule": 0,
            "ztbPayAnyTime": 0
        },
        {
            "accountType": 1,
            "amount": 5383535,
            "assetMode": 0,
            "canBidAmount": 5383535,
            "detailTitle": "企业借款 TZCJGPWOTTE",
            "detailUrl": "https://m.huli.com/1.1/bid/detail/473253889446775465/zrb",
            "fedPrdType": 0,
            "id": 706530552779003033,
            "idStr": "362185008335663033",
            "interestRate": 850,
            "interestType": "协议约定年化利率",
            "isFixedRepay": 0,
            "isSeckill": 0,
            "isSelfTransfer": 0,
            "isTransfer": 1,
            "isapp": 0,
            "isfresh": 0,
            "loanType": 0,
            "percent": 0,
            "periods": "10个月28天",
            "principalDiscountRate": 10000,
            "productType": "zrb",
            "raiseInterestRate": 0,
            "realStatus": 1,
            "remainingAmounts": 0,
            "repayMode": "先息后本",
            "repayModeInt": 0,
            "status": 1,
            "statusText": "抢",
            "subType": 0,
            "title": "企业借款 TZCJGPWOTTE",
            "transRule": 0,
            "ztbPayAnyTime": 0
        },
        {
            "accountType": 1,
            "amount": 1011750,
            "assetMode": 0,
            "canBidAmount": 928282,
            "detailTitle": "信易贷 HZFM5O5OSTE",
            "detailUrl": "https://m.huli.com/1.1/bid/detail/584375860557885485/zrb",
            "fedPrdType": 0,
            "id": 817658693880115305,
            "idStr": "584310210557885265",
            "interestRate": 900,
            "interestType": "协议约定年化利率",
            "isFixedRepay": 0,
            "isSeckill": 0,
            "isSelfTransfer": 0,
            "isTransfer": 1,
            "isapp": 0,
            "isfresh": 0,
            "loanType": 0,
            "percent": 825,
            "periods": "5个月3天",
            "principalDiscountRate": 10000,
            "productType": "zrb",
            "raiseInterestRate": 0,
            "realStatus": 1,
            "remainingAmounts": 0,
            "repayMode": "先息后本",
            "repayModeInt": 0,
            "status": 1,
            "statusText": "抢",
            "subType": 0,
            "title": "信易贷 HZFM5O5OSTE",
            "transRule": 0,
            "ztbPayAnyTime": 0
        },
        {
            "accountType": 1,
            "amount": 37172,
            "assetMode": 0,
            "canBidAmount": 37172,
            "detailTitle": "企业借款 TZUWAHY1KQ5",
            "detailUrl": "https://m.huli.com/1.1/bid/detail/695470891668996565/zrb",
            "fedPrdType": 0,
            "id": 473240599446775305,
            "idStr": "584378870557885425",
            "interestRate": 850,
            "interestType": "协议约定年化利率",
            "isFixedRepay": 0,
            "isSeckill": 0,
            "isSelfTransfer": 0,
            "isTransfer": 1,
            "isapp": 0,
            "isfresh": 0,
            "loanType": 0,
            "percent": 0,
            "periods": "10个月20天",
            "principalDiscountRate": 10000,
            "productType": "zrb",
            "raiseInterestRate": 0,
            "realStatus": 1,
            "remainingAmounts": 0,
            "repayMode": "先息后本",
            "repayModeInt": 0,
            "status": 1,
            "statusText": "抢",
            "subType": 0,
            "title": "企业借款 TZUWAHY1KQ5",
            "transRule": 0,
            "ztbPayAnyTime": 0
        },
        {
            "accountType": 1,
            "amount": 20382,
            "assetMode": 0,
            "canBidAmount": 20382,
            "detailTitle": "房易贷 ZZYDSS9W4FY",
            "detailUrl": "https://m.huli.com/1.1/bid/detail/362147498335665365/zrb",
            "fedPrdType": 0,
            "id": 695409011668995325,
            "idStr": "817638303880115265",
            "interestRate": 900,
            "interestType": "协议约定年化利率",
            "isFixedRepay": 0,
            "isSeckill": 0,
            "isSelfTransfer": 0,
            "isTransfer": 1,
            "isapp": 0,
            "isfresh": 0,
            "loanType": 0,
            "percent": 0,
            "periods": "28个月22天",
            "principalDiscountRate": 10000,
            "productType": "zrb",
            "raiseInterestRate": 0,
            "realStatus": 1,
            "remainingAmounts": 0,
            "repayMode": "等额本息",
            "repayModeInt": 0,
            "status": 1,
            "statusText": "抢",
            "subType": 0,
            "title": "房易贷 ZZYDSS9W4FY",
            "transRule": 0,
            "ztbPayAnyTime": 0
        },
        {
            "accountType": 1,
            "amount": 2318501,
            "assetMode": 0,
            "canBidAmount": 2305521,
            "detailTitle": "信易贷 WZEQ9A8IQXU",
            "detailUrl": "https://m.huli.com/1.1/bid/detail/362166658335663133/zrb",
            "fedPrdType": 0,
            "id": 584369680557883293,
            "idStr": "695417161668993253",
            "interestRate": 900,
            "interestType": "协议约定年化利率",
            "isFixedRepay": 0,
            "isSeckill": 0,
            "isSelfTransfer": 0,
            "isTransfer": 1,
            "isapp": 0,
            "isfresh": 0,
            "loanType": 0,
            "percent": 56,
            "periods": "3个月25天",
            "principalDiscountRate": 10000,
            "productType": "zrb",
            "raiseInterestRate": 0,
            "realStatus": 1,
            "remainingAmounts": 0,
            "repayMode": "先息后本",
            "repayModeInt": 0,
            "status": 1,
            "statusText": "抢",
            "subType": 0,
            "title": "信易贷 WZEQ9A8IQXU",
            "transRule": 0,
            "ztbPayAnyTime": 0
        },
        {
            "accountType": 1,
            "amount": 1513167,
            "assetMode": 0,
            "canBidAmount": 1513167,
            "detailTitle": "企业借款 VZFUADSTFP7",
            "detailUrl": "https://m.huli.com/1.1/bid/detail/473280799446775465/zrb",
            "fedPrdType": 0,
            "id": 473343329446773133,
            "idStr": "584383720557885325",
            "interestRate": 850,
            "interestType": "协议约定年化利率",
            "isFixedRepay": 0,
            "isSeckill": 0,
            "isSelfTransfer": 0,
            "isTransfer": 1,
            "isapp": 0,
            "isfresh": 0,
            "loanType": 0,
            "percent": 0,
            "periods": "9个月14天",
            "principalDiscountRate": 10000,
            "productType": "zrb",
            "raiseInterestRate": 0,
            "realStatus": 1,
            "remainingAmounts": 0,
            "repayMode": "先息后本",
            "repayModeInt": 0,
            "status": 1,
            "statusText": "抢",
            "subType": 0,
            "title": "企业借款 VZFUADSTFP7",
            "transRule": 0,
            "ztbPayAnyTime": 0
        }
    ],
    "errorCode": 0
}